MANIFEST.in
requirements.txt
setup.py
src/MurmurHash3.c
src/MurmurHash3.h
src/_pybloof.c
src/_pybloof.pyx
src/pybloof.py
src/pybloof.egg-info/PKG-INFO
src/pybloof.egg-info/SOURCES.txt
src/pybloof.egg-info/dependency_links.txt
src/pybloof.egg-info/not-zip-safe
src/pybloof.egg-info/requires.txt
src/pybloof.egg-info/top_level.txt
tests/test_bf.py
tests/test_mhash.py
tests/test_probability.py