Metadata-Version: 1.0
Name: pybloof
Version: 0.7
Summary: A high performance python bloom filter thing.
Home-page: http://github.com/jhgg/pybloof
Author: Jake Heinz
Author-email: me@jh.gg
License: MIT License
Platform: UNKNOWN
